[
  {
    "date": "2025-09-29",
    "time": "09:11:42",
    "execution_number": 1,
    "status": "success",
    "details": "Rapport généré avec succès (Exécution #1/4) - API: success"
  },
  {
    "date": "2025-09-29",
    "time": "08:16:35",
    "execution_number": 1,
    "status": "success",
    "details": "Rapport généré avec succès (Exécution #1/4) - API: success"
  },
  {
    "date": "2025-09-29",
    "time": "07:25:39",
    "execution_number": 1,
    "status": "success",
    "details": "Rapport généré avec succès (Exécution #1/4) - API: success"
  },
  {
    "date": "2025-09-29",
    "time": "06:30:05",
    "execution_number": 1,
    "status": "success",
    "details": "Rapport généré avec succès (Exécution #1/4) - API: success"
  },
  {
    "date": "2025-09-28",
    "time": "09:08:45",
    "execution_number": 1,
    "status": "success",
    "details": "Rapport généré avec succès (Exécution #1/4) - API: success"
  },
  {
    "date": "2025-09-28",
    "time": "08:12:59",
    "execution_number": 1,
    "status": "success",
    "details": "Rapport généré avec succès (Exécution #1/4) - API: success"
  },
  {
    "date": "2025-09-28",
    "time": "07:20:49",
    "execution_number": 1,
    "status": "success",
    "details": "Rapport généré avec succès (Exécution #1/4) - API: success"
  },
  {
    "date": "2025-09-28",
    "time": "06:26:08",
    "execution_number": 1,
    "status": "success",
    "details": "Rapport généré avec succès (Exécution #1/4) - API: success"
  },
  {
    "date": "2025-09-27",
    "time": "09:08:40",
    "execution_number": 1,
    "status": "success",
    "details": "Rapport généré avec succès (Exécution #1/4) - API: error"
  },
  {
    "date": "2025-09-27",
    "time": "08:13:02",
    "execution_number": 1,
    "status": "success",
    "details": "Rapport généré avec succès (Exécution #1/4) - API: success"
  },
  {
    "date": "2025-09-27",
    "time": "07:19:45",
    "execution_number": 1,
    "status": "success",
    "details": "Rapport généré avec succès (Exécution #1/4) - API: success"
  },
  {
    "date": "2025-09-27",
    "time": "06:24:32",
    "execution_number": 1,
    "status": "success",
    "details": "Rapport généré avec succès (Exécution #1/4) - API: success"
  },
  {
    "date": "2025-09-26",
    "time": "09:10:21",
    "execution_number": 1,
    "status": "success",
    "details": "Rapport généré avec succès (Exécution #1/4) - API: success"
  },
  {
    "date": "2025-09-26",
    "time": "08:16:04",
    "execution_number": 1,
    "status": "success",
    "details": "Rapport généré avec succès (Exécution #1/4) - API: success"
  },
  {
    "date": "2025-09-26",
    "time": "07:24:20",
    "execution_number": 1,
    "status": "success",
    "details": "Rapport généré avec succès (Exécution #1/4) - API: success"
  },
  {
    "date": "2025-09-26",
    "time": "06:28:28",
    "execution_number": 1,
    "status": "success",
    "details": "Rapport généré avec succès (Exécution #1/4) - API: success"
  },
  {
    "date": "2025-09-25",
    "time": "09:10:25",
    "status": "success",
    "details": "Rapport généré avec succès - API: success"
  },
  {
    "date": "2025-09-24",
    "time": "20:20:01",
    "status": "success",
    "details": "Rapport généré avec succès - API: success"
  },
  {
    "date": "2025-09-24",
    "time": "20:19:18",
    "status": "success",
    "details": "Rapport généré avec succès - API: success"
  },
  {
    "date": "2025-09-24",
    "time": "20:18:52",
    "status": "success",
    "details": "Rapport généré avec succès - API: success"
  }
]